fosforml/__init__.py
fosforml/api.py
fosforml/constants.py
fosforml/decorators.py
fosforml/exceptions.py
fosforml/utils.py
fosforml/validators.py
fosforml/model_manager/__init__.py
fosforml/model_manager/model.py
fosforml/model_manager/model_metrics.py
fosforml/model_manager/model_registry.py
fosforml/model_manager/snowflakesession.py
fosforml/model_manager/utilities.py
fosforml/schema/__init__.py
fosforml/schema/base_schema_generator.py
fosforml/schema/numpy_schema_generator.py
fosforml/schema/pandas_schema_generator.py
tests/__init__.py
tests/conftest.py
tests/test_register_model.py
tests/test_schema.py
fosforml-1.1.9.dist-info/METADATA
fosforml-1.1.9.dist-info/WHEEL
fosforml-1.1.9.dist-info/top_level.txt
fosforml-1.1.9.dist-info/RECORD
