Metadata-Version: 2.1
Name: fosforml
Version: 1.1.9
Summary: A Python package for registering machine learning models directly to the Snowflake Model Registry, leveraging Snowflake ML capabilities.
Home-page: https://gitlab.fosfor.com/fosfor-decision-cloud/intelligence/refract-sdk.git
Author: Mahesh Gadipea
Author-email: mahesh.gadipea@fosfor.com
Project-URL: Product, https://www.fosfor.com/
Project-URL: Source, https://gitlab.fosfor.com/fosfor-decision-cloud/intelligence/refract-sdk/-/tree/main/fosforml?ref_type=heads
Keywords: fosforml
Classifier: Programming Language :: Python :: 3.8
Requires-Dist: cloudpickle==2.2.1
Requires-Dist: snowflake-ml-python==1.5.0; python_version <= "3.9"
Requires-Dist: snowflake-ml-python==1.5.1; python_version == "3.10"
Requires-Dist: snowflake-ml-python==1.5.3; python_version >= "3.11"
Requires-Dist: scikit-learn==1.3.2
